Metadata-Version: 1.1
Name: idna-ssl
Version: 0.0.1
Summary: Patch ssl.match_hostname for Unicode(inda) domains support
Home-page: https://github.com/wikibusiness/idna_ssl
Author: OCEAN S.A.
Author-email: osf@ocean.io
License: UNKNOWN
Keywords: ssl,Unicode,idna,match_hostname
Platform: UNKNOWN
Classifier: Development Status :: 4 - Beta
Classifier: Intended Audience :: Developers
Classifier: License :: OSI Approved :: MIT License
Classifier: Programming Language :: Python
Classifier: Programming Language :: Python :: 3
Classifier: Programming Language :: Python :: 3.3
Classifier: Programming Language :: Python :: 3.4
Classifier: Programming Language :: Python :: 3.5
Classifier: Programming Language :: Python :: 3.6
